google/adk_community/README.md
google/adk_community/__init__.py
google/adk_community/version.py
google/adk_community/sessions/__init__.py
google/adk_community/sessions/redis_session_service.py
google/adk_community/sessions/utils.py
google_adk_community-0.1.0.dist-info/licenses/LICENSE
google_adk_community-0.1.0.dist-info/WHEEL
google_adk_community-0.1.0.dist-info/METADATA
google_adk_community-0.1.0.dist-info/RECORD
