Metadata-Version: 2.4
Name: google-adk-community
Version: 0.1.0
Summary: Agent Development Kit Community Repo
Author-email: Google LLC <googleapis-packages@google.com>
Requires-Python: >=3.9
Classifier: Typing :: Typed
Classifier: Intended Audience :: Developers
Classifier: Intended Audience :: Science/Research
Classifier: Programming Language :: Python
Classifier: Programming Language :: Python :: 3
Classifier: Programming Language :: Python :: 3.9
Classifier: Programming Language :: Python :: 3.10
Classifier: Programming Language :: Python :: 3.11
Classifier: Programming Language :: Python :: 3.12
Classifier: Programming Language :: Python :: 3.13
Classifier: Operating System :: OS Independent
Classifier: Topic :: Software Development :: Libraries :: Python Modules
Classifier: License :: OSI Approved :: Apache Software License
License-File: LICENSE
Requires-Dist: google-genai>=1.21.1, <2.0.0
Requires-Dist: google-adk
Requires-Dist: redis>=5.0.0, <6.0.0
Requires-Dist: orjson>=3.11.3
Requires-Dist: pytest>=8.4.2 ; extra == "test"
Requires-Dist: pytest-asyncio>=1.2.0 ; extra == "test"
Project-URL: changelog, https://github.com/google/adk-python-community/blob/main/CHANGELOG.md
Project-URL: documentation, https://google.github.io/adk-docs/
Project-URL: homepage, https://google.github.io/adk-docs/
Project-URL: repository, https://github.com/google/adk-python-community
Provides-Extra: test
